{
  "classifiers": {
    "residentpermit_workflow": {
      "code": "RESIDENT_PERMIT_REPLACEMENT",
      "name": "Resident Permit Process",
      "description": "Work Resident Permit Process Flow",
      "valid_from": "2024-01-01",
      "valid_to": "2030-01-01",
      "classifier_items": [
        {
          "code": "VERIFICATION",
          "name": "Res Verification",
          "description": "Verification Task",
          "mandatory": false,
          "sequence": 1,
          "valid_from": "2024-01-01",
          "valid_to": "2030-01-01",
          "next_activity_name": "VETTING",
          "create_task_rules": {
            "current_status": "NEW",
            "system_verification": "validated"
          }
        },
        {
          "code": "FINAL_DECISION",
          "name": "Res Production Decision",
          "description": "Permit Production Task",
          "sequence": 3,
          "mandatory": false,
          "valid_from": "2024-01-01",
          "valid_to": "2030-01-01",
          "next_activity_name": "END",
          "create_task_rules": {
            "or": {"verification_decision": "ACCEPTED|REJECTED"},
            "current_status": "VERIFICATION"
          }
        }
      ]
    }
  }
}
