{
  "classifiers": {
    "attachment_documents": {
            "code": "ATTACHMENT_DOCUMENTS",
            "name": "ATTACHMENT DOCUMENTS",
            "process_name": "WORK_RESIDENT_PERMIT",
            "description": "A list of document to attach",
            "valid_from": "2024-01-01",
            "valid_to": "2030-01-01",
            "classifier_items": [
              {
                "code":  "PASSPORT_COPY",
                "name":  "PASSPORT COPY",
                "description": "Scanned passport page 1 copy.",
                "application_type": "WORK_PERMIT_ONLY,WORK_PERMIT_EMERGENCY,WORK_PERMIT_EXCEPTION,WORK_PERMIT_REPLACEMENT",
                "mandatory": true,
                "valid_from": "2024-01-01",
                "valid_to": "2030-01-01"
              }, {
                "code":  "PASSPORT_PHOTO",
                "name":  "PASSPORT PHOTO",
                "application_type": "WORK_PERMIT_ONLY,WORK_PERMIT_EMERGENCY,WORK_PERMIT_EXCEPTION,WORK_PERMIT_REPLACEMENT",
                "description": "Passport photo",
                "mandatory": true,
                "valid_from": "2024-01-01",
                "valid_to": "2030-01-01"
              }, {
                "code":  "COVER_LETTER",
                "name":  "COVER LETTER",
                "application_type": "WORK_PERMIT_ONLY,WORK_PERMIT_EMERGENCY,WORK_PERMIT_EXCEPTION,WORK_PERMIT_REPLACEMENT",
                "description": "Cover letter",
                "mandatory": true,
                "valid_from": "2024-01-01",
                "valid_to": "2030-01-01"
              },
              {
                "code":  "CONFIRMATION_LETTER",
                "name":  "CONFIRMATION LETTER",
                "application_type": "WORK_PERMIT_ONLY,WORK_PERMIT_EMERGENCY,WORK_PERMIT_EXCEPTION,WORK_PERMIT_REPLACEMENT",
                "description": "Confirmation Letter",
                "mandatory": false,
                "valid_from": "2024-01-01",
                "valid_to": "2030-01-01"
              },{
                "code":  "CERTIFIED_COPY_OF_OMANG",
                "name":  "CERTIFIED COPY OF OMANG",
                "application_type": "WORK_PERMIT_ONLY,WORK_PERMIT_EMERGENCY,WORK_PERMIT_EXCEPTION,WORK_PERMIT_REPLACEMENT",
                "description": "Certified copy of omang",
                "mandatory": false,
                "valid_from": "2024-01-01",
                "valid_to": "2030-01-01"
              },{
                "code":  "MARRIAGE CERTIFICATE",
                "name":  "MARRIAGE_CERTIFICATE",
                "application_type": "WORK_PERMIT_ONLY,WORK_PERMIT_EMERGENCY,WORK_PERMIT_EXCEPTION,WORK_PERMIT_REPLACEMENT",
                "description": "Certified copy of Marriage Certificate",
                "mandatory": false,
                "valid_from": "2024-01-01",
                "valid_to": "2030-01-01"
              }
            ]
    }
  }
}
